kestrel_datasource_stixbundle/__init__.py
kestrel_datasource_stixbundle/interface.py
kestrel_datasource_stixbundle-1.8.0.dist-info/METADATA
kestrel_datasource_stixbundle-1.8.0.dist-info/WHEEL
kestrel_datasource_stixbundle-1.8.0.dist-info/top_level.txt
kestrel_datasource_stixbundle-1.8.0.dist-info/RECORD
